ssd.py
ssd-1.0.0.dist-info/DESCRIPTION.rst
ssd-1.0.0.dist-info/METADATA
ssd-1.0.0.dist-info/RECORD
ssd-1.0.0.dist-info/WHEEL
ssd-1.0.0.dist-info/metadata.json
ssd-1.0.0.dist-info/top_level.txt
ssd-1.0.0.dist-info/zip-safe
