Metadata-Version: 2.0
Name: ssd
Version: 1.0.0
Summary: Solid-State Drive Checker
Home-page: https://github.com/vuolter/pySSD
Author: Walter Purcaro
Author-email: vuolter@gmail.com
License: MIT
Download-URL: https://github.com/vuolter/pySSD/releases
Keywords: ssd pyssd
Platform: any
Classifier: Development Status :: 5 - Production/Stable
Classifier: Intended Audience :: Developers
Classifier: Intended Audience :: End Users/Desktop
Classifier: License :: OSI Approved :: MIT License
Classifier: Natural Language :: English
Classifier: Operating System :: MacOS :: MacOS X
Classifier: Operating System :: Microsoft :: Windows
Classifier: Operating System :: POSIX
Classifier: Programming Language :: Python
Classifier: Programming Language :: Python :: 2
Classifier: Programming Language :: Python :: 2.6
Classifier: Programming Language :: Python :: 2.7
Classifier: Programming Language :: Python :: 3
Classifier: Programming Language :: Python :: 3.3
Classifier: Programming Language :: Python :: 3.4
Classifier: Programming Language :: Python :: 3.5
Classifier: Programming Language :: Python :: 3.6
Classifier: Topic :: Software Development :: Libraries :: Python Modules
Classifier: Topic :: System
Classifier: Topic :: System :: Filesystems
Classifier: Topic :: Utilities
Requires-Python: >=2.6,!=3.0,!=3.1,!=3.2
Requires-Dist: psutil; os_name != "nt"
Requires-Dist: pypiwin32 (>=154); os_name == "nt"
Requires-Dist: wmi; os_name == "nt"
